{"subscriptions": [{"id": "9b717a5d-ca3e-4e01-88c3-c3261f181c5b", "name": "Microsoft Azure Sponsorship", "state": "Disabled", "user": {"name": "mathew.kim@sckcloud.co.kr", "type": "user", "cloudShellID": true}, "isDefault": false, "tenantId": "f9b517f3-0777-422b-93c2-8212ee9cc71a", "environmentName": "AzureCloud", "homeTenantId": "f9b517f3-0777-422b-93c2-8212ee9cc71a", "managedByTenants": []}, {"id": "c294667c-0ec6-4197-ba31-23324d751d71", "name": "Microsoft Azure \uc2a4\ud3f0\uc11c\uc27d", "state": "Disabled", "user": {"name": "mathew.kim@sckcloud.co.kr", "type": "user", "cloudShellID": true}, "isDefault": false, "tenantId": "f9b517f3-0777-422b-93c2-8212ee9cc71a", "environmentName": "AzureCloud", "homeTenantId": "f9b517f3-0777-422b-93c2-8212ee9cc71a", "managedByTenants": []}, {"id": "c02ab7bb-5521-400e-bd8b-eeeec60929b4", "name": "\ubbf8\uad70\uae30\uc9c0\uc774\uc804\uc0ac\uc5c5\ub2e8_PoC", "state": "Enabled", "user": {"name": "mathew.kim@sckcloud.co.kr", "type": "user", "cloudShellID": true}, "isDefault": false, "tenantId": "f9b517f3-0777-422b-93c2-8212ee9cc71a", "environmentName": "AzureCloud", "homeTenantId": "f9b517f3-0777-422b-93c2-8212ee9cc71a", "managedByTenants": []}, {"id": "1211a5a2-7ad9-4b7f-b15c-15e0ee6cb276", "name": "SPLUNK_SCK", "state": "Enabled", "user": {"name": "mathew.kim@sckcloud.co.kr", "type": "user", "cloudShellID": true}, "isDefault": false, "tenantId": "f9b517f3-0777-422b-93c2-8212ee9cc71a", "environmentName": "AzureCloud", "homeTenantId": "f9b517f3-0777-422b-93c2-8212ee9cc71a", "managedByTenants": []}, {"id": "b521dcc1-208e-4b7f-b66c-c0dcad818a6d", "name": "SPLUNK-SCK", "state": "Enabled", "user": {"name": "mathew.kim@sckcloud.co.kr", "type": "user", "cloudShellID": true}, "isDefault": false, "tenantId": "f9b517f3-0777-422b-93c2-8212ee9cc71a", "environmentName": "AzureCloud", "homeTenantId": "f9b517f3-0777-422b-93c2-8212ee9cc71a", "managedByTenants": []}, {"id": "287b18b9-d3c0-40a3-be04-353c83a23a15", "name": "SCK_SPLUNK", "state": "Enabled", "user": {"name": "mathew.kim@sckcloud.co.kr", "type": "user", "cloudShellID": true}, "isDefault": false, "tenantId": "f9b517f3-0777-422b-93c2-8212ee9cc71a", "environmentName": "AzureCloud", "homeTenantId": "f9b517f3-0777-422b-93c2-8212ee9cc71a", "managedByTenants": []}, {"id": "aca6a842-5fe1-4fc4-8f34-03ed34296924", "name": "Microsoft Azure \uc2a4\ud3f0\uc11c\uc27d", "state": "Enabled", "user": {"name": "mathew.kim@sckcloud.co.kr", "type": "user", "cloudShellID": true}, "isDefault": true, "tenantId": "f9b517f3-0777-422b-93c2-8212ee9cc71a", "environmentName": "AzureCloud", "homeTenantId": "f9b517f3-0777-422b-93c2-8212ee9cc71a", "managedByTenants": [{"tenantId": "2f4a9838-26b7-47ee-be60-ccc1fdec5953"}]}], "installationId": "7c8b6d4e-cf30-11ea-b236-0a580af4cf08"}